iglabel-0.0.7.dist-info/METADATA
iglabel-0.0.7.dist-info/WHEEL
iglabel/__init__.py
iglabel/lib/__init__.py
iglabel/lib/citation.py
iglabel/lib/imgt_annotations.py
iglabel/scripts/__init__.py
iglabel/scripts/create_overview_seq.py
iglabel/scripts/label_sequences.py
iglabel-0.0.7.dist-info/RECORD
