Metadata-Version: 2.1
Name: IGLabel
Version: 0.0.7
Summary: This package will give you an easy way to label your sequences according to common standards in immunology.
Author-Email: Nils Hofmann <nilhof01@gmail.com>
License: MIT
Requires-Python: >=3.7
